dbt/adapters/mariadb/__init__.py
dbt/adapters/mariadb/__version__.py
dbt/adapters/mariadb/column.py
dbt/adapters/mariadb/connections.py
dbt/adapters/mariadb/impl.py
dbt/adapters/mariadb/relation.py
dbt/adapters/mysql/__init__.py
dbt/adapters/mysql/__version__.py
dbt/adapters/mysql/column.py
dbt/adapters/mysql/connections.py
dbt/adapters/mysql/impl.py
dbt/adapters/mysql/relation.py
dbt/adapters/mysql5/__init__.py
dbt/adapters/mysql5/__version__.py
dbt/adapters/mysql5/column.py
dbt/adapters/mysql5/connections.py
dbt/adapters/mysql5/impl.py
dbt/adapters/mysql5/relation.py
dbt/include/mariadb/__init__.py
dbt/include/mariadb/dbt_project.yml
dbt/include/mariadb/sample_profiles.yml
dbt/include/mariadb/macros/adapters.sql
dbt/include/mariadb/macros/catalog.sql
dbt/include/mariadb/macros/materializations/incremental/helpers.sql
dbt/include/mariadb/macros/materializations/incremental/incremental.sql
dbt/include/mariadb/macros/materializations/seed/seed.sql
dbt/include/mariadb/macros/materializations/snapshot/snapshot.sql
dbt/include/mariadb/macros/materializations/snapshot/snapshot_merge.sql
dbt/include/mariadb/macros/materializations/snapshot/strategies.sql
dbt/include/mariadb/macros/materializations/test/test.sql
dbt/include/mysql/__init__.py
dbt/include/mysql/dbt_project.yml
dbt/include/mysql/sample_profiles.yml
dbt/include/mysql/macros/adapters.sql
dbt/include/mysql/macros/catalog.sql
dbt/include/mysql/macros/materializations/incremental/helpers.sql
dbt/include/mysql/macros/materializations/incremental/incremental.sql
dbt/include/mysql/macros/materializations/seed/seed.sql
dbt/include/mysql/macros/materializations/snapshot/snapshot.sql
dbt/include/mysql/macros/materializations/snapshot/snapshot_merge.sql
dbt/include/mysql/macros/materializations/snapshot/strategies.sql
dbt/include/mysql/macros/materializations/test/test.sql
dbt/include/mysql5/__init__.py
dbt/include/mysql5/dbt_project.yml
dbt/include/mysql5/sample_profiles.yml
dbt/include/mysql5/macros/adapters.sql
dbt_mysql-1.7.0.dist-info/LICENSE
dbt_mysql-1.7.0.dist-info/METADATA
dbt_mysql-1.7.0.dist-info/WHEEL
dbt_mysql-1.7.0.dist-info/top_level.txt
dbt_mysql-1.7.0.dist-info/RECORD
