Metadata-Version: 2.1
Name: dbt-mysql
Version: 1.7.0
Summary: The MySQL adapter plugin for dbt
Home-page: https://github.com/dbeatty10/dbt-mysql
Author: Doug Beatty
Author-email: doug.beatty@gmail.com
Classifier: Development Status :: 3 - Alpha
Classifier: License :: OSI Approved :: Apache Software License
Classifier: Operating System :: Microsoft :: Windows
Classifier: Operating System :: MacOS :: MacOS X
Classifier: Operating System :: POSIX :: Linux
Classifier: Programming Language :: Python :: 3.7
Classifier: Programming Language :: Python :: 3.8
Classifier: Programming Language :: Python :: 3.9
Requires-Python: >=3.7
License-File: LICENSE
Requires-Dist: dbt-core~=1.7.0
Requires-Dist: mysql-connector-python>=8.0.0
